cliver/__init__.py
cliver/builtin_tools.py
cliver/cli.py
cliver/cliver_run.py
cliver/commands/__init__.py
cliver/commands/capabilities.py
cliver/commands/chat.py
cliver/commands/config.py
cliver/commands/llm.py
cliver/commands/mcp.py
cliver/commands/workflow.py
cliver/config.py
cliver/constants.py
cliver/llm/__init__.py
cliver/llm/base.py
cliver/llm/llm.py
cliver/llm/media_utils.py
cliver/llm/ollama_engine.py
cliver/llm/openai_engine.py
cliver/mcp_server_caller.py
cliver/media.py
cliver/media_handler.py
cliver/model_capabilities.py
cliver/prompt_enhancer.py
cliver/tools/__init__.py
cliver/util.py
cliver/workflow/README.md
cliver/workflow/__init__.py
cliver/workflow/persistence/__init__.py
cliver/workflow/persistence/base.py
cliver/workflow/persistence/local_cache.py
cliver/workflow/steps/__init__.py
cliver/workflow/steps/base.py
cliver/workflow/steps/function_step.py
cliver/workflow/steps/human_step.py
cliver/workflow/steps/llm_step.py
cliver/workflow/steps/workflow_step.py
cliver/workflow/workflow_executor.py
cliver/workflow/workflow_manager_base.py
cliver/workflow/workflow_manager_local.py
cliver/workflow/workflow_models.py
cliver-0.0.1.dist-info/WHEEL
cliver-0.0.1.dist-info/entry_points.txt
cliver-0.0.1.dist-info/METADATA
cliver-0.0.1.dist-info/RECORD
